{"errors":[],"warnings":[],"namedChunkGroups":{"app":{"chunks":[5,0,1],"assets":["webpack-runtime-8d433207df097716f822.js","webpack-runtime-8d433207df097716f822.js.map","commons.ca85b1deeda3d6a407a0.css","commons-81d9324e06ad4fbfd470.js","commons-81d9324e06ad4fbfd470.js.map","app-64dd2c57bf518f02cad9.js","app-64dd2c57bf518f02cad9.js.map"],"children":{},"childAssets":{}},"component---src-pages-404-js":{"chunks":[0,2],"assets":["commons.ca85b1deeda3d6a407a0.css","commons-81d9324e06ad4fbfd470.js","commons-81d9324e06ad4fbfd470.js.map","component---src-pages-404-js-5a8a4662bf4310a7c8b3.js","component---src-pages-404-js-5a8a4662bf4310a7c8b3.js.map"],"children":{},"childAssets":{}},"component---src-pages-index-js":{"chunks":[0,3],"assets":["commons.ca85b1deeda3d6a407a0.css","commons-81d9324e06ad4fbfd470.js","commons-81d9324e06ad4fbfd470.js.map","component---src-pages-index-js-8094e59d2dccf6b62c8d.js","component---src-pages-index-js-8094e59d2dccf6b62c8d.js.map"],"children":{},"childAssets":{}},"component---src-pages-page-2-js":{"chunks":[0,4],"assets":["commons.ca85b1deeda3d6a407a0.css","commons-81d9324e06ad4fbfd470.js","commons-81d9324e06ad4fbfd470.js.map","component---src-pages-page-2-js-a32e137a01c6e6f9a532.js","component---src-pages-page-2-js-a32e137a01c6e6f9a532.js.map"],"children":{},"childAssets":{}}},"assetsByChunkName":{"app":["webpack-runtime-8d433207df097716f822.js","commons.ca85b1deeda3d6a407a0.css","commons-81d9324e06ad4fbfd470.js","app-64dd2c57bf518f02cad9.js"],"component---src-pages-404-js":["commons.ca85b1deeda3d6a407a0.css","commons-81d9324e06ad4fbfd470.js","component---src-pages-404-js-5a8a4662bf4310a7c8b3.js"],"component---src-pages-index-js":["commons.ca85b1deeda3d6a407a0.css","commons-81d9324e06ad4fbfd470.js","component---src-pages-index-js-8094e59d2dccf6b62c8d.js"],"component---src-pages-page-2-js":["commons.ca85b1deeda3d6a407a0.css","commons-81d9324e06ad4fbfd470.js","component---src-pages-page-2-js-a32e137a01c6e6f9a532.js"]}}